cachemonCache/__init__.py
cachemonCache/setup0.py
cachemonCache/bench/__init__.py
cachemonCache/bench/benchmark.py
cachemonCache/bench/trace_reader.py
cachemonCache/bench/trace_replay.py
cachemonCache/cache/__init__.py
cachemonCache/cache/cache.py
cachemonCache/cache/cacheDecorator.py
cachemonCache/cache/clock.py
cachemonCache/cache/fifo.py
cachemonCache/cache/lru.py
cachemonCache/cache/s3fifo.py
cachemonCache/cache/sieve.py
cachemoncache-0.0.2.dist-info/METADATA
cachemoncache-0.0.2.dist-info/WHEEL
cachemoncache-0.0.2.dist-info/licenses/LICENSE
cachemoncache-0.0.2.dist-info/RECORD
