Metadata-Version: 2.1
Name: cachemonCache
Version: 0.0.2
Summary: a cache library with dict interface
Project-URL: Homepage, https://github.com/cachemon/py-cachemonCache
Project-URL: Source, https://github.com/cachemon/py-cachemonCache
Author: Juncheng Yang
License-Expression: MIT
License-File: LICENSE
Keywords: cache,dict,fast,lru,s3fifo,sieve
Classifier: Development Status :: 4 - Beta
Classifier: Intended Audience :: Developers
Classifier: License :: OSI Approved :: MIT License
Classifier: Operating System :: OS Independent
Classifier: Operating System :: POSIX
Classifier: Programming Language :: C
Classifier: Programming Language :: Python :: 3
Classifier: Programming Language :: Python :: 3.7
Classifier: Programming Language :: Python :: 3.8
Classifier: Programming Language :: Python :: 3.9
Classifier: Programming Language :: Python :: 3.10
Classifier: Programming Language :: Python :: 3.11
Classifier: Topic :: Software Development :: Libraries :: Python Modules
Provides-Extra: test
Requires-Dist: pytest; extra == 'test'
